{
  "sample_id": "cdr_1_voice1_male_home_0655",
  "cdr_level": 1,
  "cdr_label": "mild",
  "scenario": "home",
  "task_type": "daily_life_description",
  "interaction_type": "one_person_description",
  "picture_reference": null,
  "speaker": {
    "speaker_id": "voice1_male",
    "voice_id": "voice1_male",
    "speaker_group": "male",
    "gender": "male",
    "split": "train"
  },
  "interviewer": {
    "speaker_id": "interviewer_neutral",
    "voice_id": "interviewer_neutral",
    "speaker_group": "interviewer"
  },
  "split": "train",
  "spoken_transcript": "我每天早上都會去菜市場買菜， 不過今天好像忘了要帶什麼。嗯，阿母說要去診所拿藥， 但我記得不太清楚是紅色的還是白色的瓶子。欸，大概是那個吧？ 反正回家再問囝仔就好。",
  "marked_transcript": "我每天早上都會去菜市場買菜，[停頓] 不過今天好像忘了要帶什麼。嗯，阿母說要去診所拿藥，[長停頓] 但我記得不太清楚是紅色的還是白色的瓶子。欸，大概是那個吧？[嘆氣] 反正回家再問囝仔就好。",
  "event_script": [
    {
      "type": "speech",
      "speaker": "patient",
      "text": "我每天早上都會去菜市場買菜"
    },
    {
      "type": "pause",
      "duration_ms": 721
    },
    {
      "type": "speech",
      "speaker": "patient",
      "text": "不過今天好像忘了要帶什麼。嗯，阿母說要去診所拿藥"
    },
    {
      "type": "pause",
      "duration_ms": 1408
    },
    {
      "type": "speech",
      "speaker": "patient",
      "text": "但我記得不太清楚是紅色的還是白色的瓶子。欸，大概是那個吧？"
    },
    {
      "type": "sigh",
      "duration_ms": 924
    },
    {
      "type": "speech",
      "speaker": "patient",
      "text": "反正回家再問囝仔就好"
    }
  ],
  "event_stats": {
    "speech_chunk_count": 4,
    "pause_event_count": 2,
    "sigh_event_count": 1,
    "cough_event_count": 0,
    "breath_event_count": 0,
    "total_pause_ms": 3053,
    "chinese_char_count": 71
  },
  "impairment_features": {
    "hesitation_count": 4,
    "repetition_count": 1,
    "word_finding_count": 1,
    "orientation_error_count": 0,
    "memory_error_count": 1,
    "topic_drift_score": 0.29,
    "coherence_score": 0.72,
    "speech_rate_target": "slow",
    "pause_event_count": 2
  },
  "acoustic_condition": "clean",
  "acoustic_condition_info": {
    "weight": 45,
    "description": "乾淨近距離錄音，低背景噪音。"
  },
  "generation_notes": "CDR 1 mild: Shows word-finding difficulty (red vs white bottle), mild repetition, and one memory uncertainty. Speech remains coherent with natural pauses."
}