{
  "sample_id": "cdr_2_voice3_male_medicine_routine_0908",
  "cdr_level": 2,
  "cdr_label": "moderate",
  "scenario": "medicine_routine",
  "task_type": "daily_life_description",
  "interaction_type": "one_person_description",
  "picture_reference": null,
  "speaker": {
    "speaker_id": "voice3_male",
    "voice_id": "voice3_male",
    "speaker_group": "male",
    "gender": "male",
    "split": "train"
  },
  "interviewer": {
    "speaker_id": "interviewer_neutral",
    "voice_id": "interviewer_neutral",
    "speaker_group": "interviewer"
  },
  "split": "train",
  "spoken_transcript": "嗯...那個，早上啊。我通常...呃...大概九點左右會吃藥啦。藥盒在客廳那個櫃子，上面。阿母有幫我放好，但今天好像...有點亂。我先拿那個白色的瓶子，然後是藍色的...不對，好像是黃色的？記不太清楚了。然後要配水喝，對，水很重要。後來要去診所拿下一次的藥，時間好像是下午兩點？還是三點？忘記了啦。反正就是吃完藥之後，再去看醫生。那個櫃子...呃...記得有幾個瓶子，但是名字想不起來。就吃...吃下去就好了。",
  "marked_transcript": "嗯... [停頓] 那個，早上啊。我通常... [長停頓] 呃...大概九點左右會吃藥啦。藥盒在客廳那個櫃子，上面。阿母有幫我放好，但今天好像... [停頓] 有點亂。我先拿那個白色的瓶子，然後是藍色的... [嘆氣] 不對，好像是黃色的？記不太清楚了。然後要配水喝，對，水很重要。後來要去診所拿下一次的藥，時間好像是下午兩點？還是三點？忘記了啦。反正就是吃完藥之後，再去看醫生。那個櫃子... [停頓] 呃...記得有幾個瓶子，但是名字想不起來。就吃... [停頓] 吃下去就好了。",
  "event_script": [
    {
      "type": "speech",
      "speaker": "patient",
      "text": "嗯"
    },
    {
      "type": "pause",
      "duration_ms": 600
    },
    {
      "type": "speech",
      "speaker": "patient",
      "text": "那個，早上啊。我通常"
    },
    {
      "type": "pause",
      "duration_ms": 1400
    },
    {
      "type": "speech",
      "speaker": "patient",
      "text": "呃"
    },
    {
      "type": "speech",
      "speaker": "patient",
      "text": "大概九點左右會吃藥啦。藥盒在客廳那個櫃子，上面。阿母有幫我放好，但今天好像"
    },
    {
      "type": "pause",
      "duration_ms": 500
    },
    {
      "type": "speech",
      "speaker": "patient",
      "text": "有點亂。我先拿那個白色的瓶子，然後是藍色的"
    },
    {
      "type": "sigh",
      "duration_ms": 900
    },
    {
      "type": "speech",
      "speaker": "patient",
      "text": "不對，好像是黃色的？記不太清楚了。然後要配水喝，對，水很重要。後來要去診所拿下一次的藥，時間好像是下午兩點？還是三點？忘記了啦。反正就是吃完藥之後，再去看醫生。那個櫃子"
    },
    {
      "type": "pause",
      "duration_ms": 700
    },
    {
      "type": "speech",
      "speaker": "patient",
      "text": "呃"
    },
    {
      "type": "speech",
      "speaker": "patient",
      "text": "記得有幾個瓶子，但是名字想不起來。就吃"
    },
    {
      "type": "pause",
      "duration_ms": 500
    },
    {
      "type": "speech",
      "speaker": "patient",
      "text": "吃下去就好了"
    }
  ],
  "event_stats": {
    "speech_chunk_count": 9,
    "pause_event_count": 5,
    "sigh_event_count": 1,
    "cough_event_count": 0,
    "breath_event_count": 0,
    "total_pause_ms": 4600,
    "chinese_char_count": 158
  },
  "impairment_features": {
    "hesitation_count": 9,
    "repetition_count": 2,
    "word_finding_count": 4,
    "orientation_error_count": 2,
    "memory_error_count": 4,
    "topic_drift_score": 0.45,
    "coherence_score": 0.52,
    "speech_rate_target": "very_slow",
    "pause_event_count": 5
  },
  "acoustic_condition": "clinic_room_noise",
  "acoustic_condition_info": {
    "weight": 25,
    "description": "診間環境，輕微背景聲與空調聲。"
  }
}