{
  "sample_id": "cdr_0_5_voice1_male_family_0381",
  "cdr_level": 0.5,
  "cdr_label": "very_mild",
  "scenario": "family",
  "task_type": "daily_life_description",
  "interaction_type": "one_person_description",
  "picture_reference": null,
  "speaker": {
    "speaker_id": "voice1_male",
    "voice_id": "voice1_male",
    "speaker_group": "male",
    "gender": "male",
    "split": "test"
  },
  "interviewer": {
    "speaker_id": "interviewer_neutral",
    "voice_id": "interviewer_neutral",
    "speaker_group": "interviewer"
  },
  "split": "test",
  "spoken_transcript": "今天早上我去市場買菜，那個，先去蔬菜攤看了一下，然後再去肉鋪拿點肉。喔，還有要去藥局拿藥，因為醫生說要繼續吃藥控制血壓。",
  "marked_transcript": "今天早上我去市場買菜，[停頓] 那個，先去蔬菜攤看了一下，然後再去肉鋪拿點肉。[長停頓] 喔，還有要去藥局拿藥，因為醫生說要繼續吃藥控制血壓。",
  "event_script": [
    {
      "type": "speech",
      "speaker": "patient",
      "text": "今天早上我去市場買菜，"
    },
    {
      "type": "pause",
      "duration_ms": 600
    },
    {
      "type": "speech",
      "speaker": "patient",
      "text": "那個，先去蔬菜攤看了一下，然後再去肉鋪拿點肉。"
    },
    {
      "type": "pause",
      "duration_ms": 1500
    },
    {
      "type": "speech",
      "speaker": "patient",
      "text": "喔，還有要去藥局拿藥，因為醫生說要繼續吃藥控制血壓。"
    }
  ],
  "event_stats": {
    "speech_chunk_count": 3,
    "pause_event_count": 2,
    "sigh_event_count": 0,
    "cough_event_count": 0,
    "breath_event_count": 0,
    "total_pause_ms": 2100,
    "chinese_char_count": 53
  },
  "impairment_features": {
    "hesitation_count": 1,
    "repetition_count": 0,
    "word_finding_count": 0,
    "orientation_error_count": 0,
    "memory_error_count": 0,
    "topic_drift_score": 0.12,
    "coherence_score": 0.85,
    "speech_rate_target": "slightly_slow",
    "pause_event_count": 2
  },
  "acoustic_condition": "clean",
  "acoustic_condition_info": {
    "weight": 45,
    "description": "乾淨近距離錄音，低背景噪音。"
  }
}