{
  "sample_id": "cdr_1_voice1_male_clinic_0608",
  "cdr_level": 1,
  "cdr_label": "mild",
  "scenario": "clinic",
  "task_type": "daily_life_description",
  "interaction_type": "one_person_description",
  "picture_reference": null,
  "speaker": {
    "speaker_id": "voice1_male",
    "voice_id": "voice1_male",
    "speaker_group": "male",
    "gender": "male",
    "split": "val"
  },
  "interviewer": {
    "speaker_id": "interviewer_neutral",
    "voice_id": "interviewer_neutral",
    "speaker_group": "interviewer"
  },
  "split": "val",
  "spoken_transcript": "今天早上我起來，先去上廁所，然後就去洗臉。嗯...早餐吃了稀飯跟豆腐乳，好像還有個蛋，那個嘛...記不得了啦。然後我就準備要去診所拿藥，那個醫生說最近的狀況應該不錯，但是要繼續吃藥喔。",
  "marked_transcript": "今天早上我起來[停頓]，先去上廁所，然後就去洗臉。嗯...早餐吃了稀飯跟豆腐乳，好像還有個蛋，那個嘛...[停頓][長停頓]記不得了啦。然後我就準備要去診所拿藥[咳嗽]，那個醫生說最近的狀況應該不錯，但是要繼續吃藥喔。",
  "event_script": [
    {
      "type": "speech",
      "speaker": "patient",
      "text": "今天早上我起來"
    },
    {
      "type": "pause",
      "duration_ms": 600
    },
    {
      "type": "speech",
      "speaker": "patient",
      "text": "，先去上廁所，然後就去洗臉。嗯...早餐吃了稀飯跟豆腐乳"
    },
    {
      "type": "pause",
      "duration_ms": 800
    },
    {
      "type": "speech",
      "speaker": "patient",
      "text": "，好像還有個蛋，那個嘛..."
    },
    {
      "type": "speech",
      "speaker": "patient",
      "text": "記不得了啦。然後我就準備要去診所拿藥"
    },
    {
      "type": "cough",
      "duration_ms": 400
    },
    {
      "type": "speech",
      "speaker": "patient",
      "text": "，那個醫生說最近的狀況應該不錯，但是要繼續吃藥喔。"
    }
  ],
  "event_stats": {
    "speech_chunk_count": 5,
    "pause_event_count": 2,
    "sigh_event_count": 0,
    "cough_event_count": 1,
    "breath_event_count": 0,
    "total_pause_ms": 1800,
    "chinese_char_count": 77
  },
  "impairment_features": {
    "hesitation_count": 3,
    "repetition_count": 1,
    "word_finding_count": 2,
    "orientation_error_count": 0,
    "memory_error_count": 1,
    "topic_drift_score": 0.25,
    "coherence_score": 0.7,
    "speech_rate_target": "slow",
    "pause_event_count": 2
  },
  "acoustic_condition": "phone_mic_degraded",
  "acoustic_condition_info": {
    "weight": 20,
    "description": "手機麥克風錄音，音質稍微壓縮。"
  }
}